setup.py
motaword.egg-info/PKG-INFO
motaword.egg-info/SOURCES.txt
motaword.egg-info/dependency_links.txt
motaword.egg-info/requires.txt
motaword.egg-info/top_level.txt
motaword_sdk/__init__.py
motaword_sdk/exceptions.py
motaword_sdk/controllers/__init__.py
motaword_sdk/controllers/account.py
motaword_sdk/controllers/activities.py
motaword_sdk/controllers/base.py
motaword_sdk/controllers/documents.py
motaword_sdk/controllers/global_files.py
motaword_sdk/controllers/glossaries.py
motaword_sdk/controllers/info.py
motaword_sdk/controllers/projects.py
motaword_sdk/controllers/style_guides.py