Metadata-Version: 1.0
Name: motaword
Version: 0.9.1
Summary: Motaword Python SDK
Home-page: https://www.motaword.com/developer
Author: Sergey Tikhonov
Author-email: srg.tikhonov@gmail.com
License: MIT
Platform: UNKNOWN
